azlyrics/__init__.py
azlyrics/azlyrics.py
azlyrics-1.3.2.dist-info/DESCRIPTION.rst
azlyrics-1.3.2.dist-info/METADATA
azlyrics-1.3.2.dist-info/RECORD
azlyrics-1.3.2.dist-info/WHEEL
azlyrics-1.3.2.dist-info/metadata.json
azlyrics-1.3.2.dist-info/top_level.txt
