Metadata-Version: 2.0
Name: azlyrics
Version: 1.3.2
Summary: An API wrapper for azlyrics which allows you to programatically extract data
Home-page: https://github.com/adhorrig/azlyrics
Author: Adam Horrigan
Author-email: adhorrig@gmail.com
License: UNKNOWN
Download-URL: https://github.com/adhorrig/azlyrics/archive/0.1.tar.gz
Keywords: azlyrics,lyrics,albums,artists,songs,music,api
Platform: UNKNOWN
Requires-Dist: requests
Requires-Dist: beautifulsoup4
